dtb/money/__init__.py
dtb/money/conftest.py
dtb/money/money.py
dtb/money/money.pyi
dtb/money/py.typed
dtb/money/test.py
dtb.money-1.1.1.dist-info/WHEEL
dtb.money-1.1.1.dist-info/METADATA
dtb.money-1.1.1.dist-info/RECORD
